quash_mcp/__init__.py
quash_mcp/__main__.py
quash_mcp/backend_client.py
quash_mcp/models.py
quash_mcp/server.py
quash_mcp/state.py
quash_mcp/device/__init__.py
quash_mcp/device/adb_tools.py
quash_mcp/device/portal.py
quash_mcp/device/state_capture.py
quash_mcp/tools/__init__.py
quash_mcp/tools/build.py
quash_mcp/tools/configure.py
quash_mcp/tools/connect.py
quash_mcp/tools/execute.py
quash_mcp/tools/execute_v3.py
quash_mcp-1.0.0.dist-info/METADATA
quash_mcp-1.0.0.dist-info/WHEEL
quash_mcp-1.0.0.dist-info/entry_points.txt
quash_mcp-1.0.0.dist-info/RECORD
